mcp_wiki_kel/__init__.py
mcp_wiki_kel/__main__.py
mcp_wiki_kel/server.py
mcp_wiki_kel-1.0.0.dist-info/METADATA
mcp_wiki_kel-1.0.0.dist-info/WHEEL
mcp_wiki_kel-1.0.0.dist-info/entry_points.txt
mcp_wiki_kel-1.0.0.dist-info/RECORD
