Metadata-Version: 2.4
Name: mcp-wiki-kel
Version: 1.0.0
Summary: MCP Server for Wikipedia
Requires-Python: >=3.12
Requires-Dist: beautifulsoup4>=4.12.3
Requires-Dist: build>=1.2.2.post1
Requires-Dist: html2text>=2024.2.26
Requires-Dist: mcp[cli]>=1.2.0
Requires-Dist: requests>=2.32.3
Requires-Dist: twine>=6.1.0
